README.md
setup.py
ponte/__init__.py
ponte/module.py
ponte.egg-info/PKG-INFO
ponte.egg-info/SOURCES.txt
ponte.egg-info/dependency_links.txt
ponte.egg-info/requires.txt
ponte.egg-info/top_level.txt