Metadata-Version: 2.1
Name: ponte
Version: 0.0.1
Summary: A mini-library to process arrays to .json files and viceversa. Developed to pass arrays between Python and C++ through the use of json DOK files.
Home-page: https://github.com/andrewrgarcia/ponte
Author: Andrew Garcia, PhD
License: MIT
Platform: UNKNOWN
Classifier: Intended Audience :: Information Technology
Classifier: Intended Audience :: Education
Classifier: Intended Audience :: Developers
Classifier: Intended Audience :: Science/Research
Classifier: License :: OSI Approved :: MIT License
Classifier: Programming Language :: Python
Classifier: Operating System :: OS Independent
